litemultiagent/__init__.py
litemultiagent/agents/__init__.py
litemultiagent/agents/agent_type/__init__.py
litemultiagent/agents/agent_type/atomic.py
litemultiagent/agents/agent_type/composite.py
litemultiagent-0.1.5.dist-info/LICENSE
litemultiagent-0.1.5.dist-info/METADATA
litemultiagent-0.1.5.dist-info/WHEEL
litemultiagent-0.1.5.dist-info/top_level.txt
litemultiagent-0.1.5.dist-info/RECORD
