Metadata-Version: 2.1
Name: litemultiagent
Version: 0.1.5
Author: Danqing Zhang
Author-email: danqing.zhang.personal@gmail.com
Requires-Python: >=3.6
License-File: LICENSE
Requires-Dist: openai ==1.42.0
Requires-Dist: python-dotenv ==1.0.1
Requires-Dist: pydantic ==2.7.4
Requires-Dist: requests
Requires-Dist: supabase
Requires-Dist: langchain ==0.2.7
Requires-Dist: bs4 ==0.0.2
Requires-Dist: chromadb ==0.4.14
Requires-Dist: tiktoken ==0.7.0
Requires-Dist: psycopg2-binary ==2.9.9
Requires-Dist: sqlalchemy ==2.0.30
Requires-Dist: pypdf ==4.3.1
Requires-Dist: litellm ==1.42.1
Requires-Dist: langchain-community ==0.2.7
Requires-Dist: litewebagent ==0.1.7
